MANIFEST.in
README.md
requirements.txt
setup.cfg
setup.py
stl_sdk/__init__.py
stl_sdk/coral.py
stl_sdk/exceptions.py
stl_sdk/waves.py
stl_sdk.egg-info/PKG-INFO
stl_sdk.egg-info/SOURCES.txt
stl_sdk.egg-info/dependency_links.txt
stl_sdk.egg-info/not-zip-safe
stl_sdk.egg-info/requires.txt
stl_sdk.egg-info/top_level.txt
stl_sdk/atlantis/__init__.py
stl_sdk/atlantis/client.py
stl_sdk/atlantis/client_flask.py
stl_sdk/atlantis/exceptions.py
stl_sdk/atlantis/retry.py
stl_sdk/torpedo/__init__.py
stl_sdk/torpedo/client.py
stl_sdk/torpedo/client_flask.py
stl_sdk/torpedo/exceptions.py