Metadata-Version: 1.1
Name: stl-sdk
Version: 1.3.9
Summary: Spacetime Python SDK
Home-page: https://github.com/spacetimelabs/stl_sdk
Author: Spacetime Labs
Author-email: lc@spacetimelabs.ai
License: BSD
Download-URL: https://github.com/spacetimelabs/stl_sdk/tarball/1.3.9
Platform: UNKNOWN
Classifier: Development Status :: 3 - Alpha
Classifier: Intended Audience :: Developers
Classifier: Programming Language :: Python :: 3
